gaiascanlaw/__init__.py
gaiascanlaw/scanlaw.py
gaiascanlaw/data/data_gaps.fits
gaiascanlaw/data/gost_simple_1.fits
gaiascanlaw/data/gost_simple_2.fits
gaiascanlaw-0.2.0.dist-info/licenses/LICENSE
gaiascanlaw-0.2.0.dist-info/METADATA
gaiascanlaw-0.2.0.dist-info/WHEEL
gaiascanlaw-0.2.0.dist-info/top_level.txt
gaiascanlaw-0.2.0.dist-info/RECORD
