Metadata-Version: 2.4
Name: gaiascanlaw
Version: 0.2.0
Summary: gaia scan law
Home-page: https://github.com/zpenoyre/gaiascanlaw
Author: Zephyr Penoyre
Author-email: zephyrpenoyre@gmail.com
License: GNU GPLv3
License-File: LICENSE
Requires-Dist: numpy
Requires-Dist: astropy
Requires-Dist: scipy
Requires-Dist: healpy
Dynamic: author
Dynamic: author-email
Dynamic: description
Dynamic: home-page
Dynamic: license
Dynamic: license-file
Dynamic: requires-dist
Dynamic: summary
